{
    "key": "group_62af6b15dc7c2",
    "title": "Component - Button",
    "fields": [
        {
            "key": "field_62af6b7dc38b0",
            "label": "Button",
            "name": "button",
            "type": "group",
            "instructions": "",
            "required": 0,
            "conditional_logic": 0,
            "wrapper": {
                "width": "",
                "class": "",
                "id": ""
            },
            "layout": "row",
            "acfe_seamless_style": 0,
            "acfe_group_modal": 0,
            "sub_fields": [
                {
                    "key": "field_62af6b8dc38b1",
                    "label": "Button Text",
                    "name": "button_text",
                    "type": "text",
                    "instructions": "",
                    "required": 0,
                    "conditional_logic": 0,
                    "wrapper": {
                        "width": "",
                        "class": "",
                        "id": ""
                    },
                    "default_value": "",
                    "placeholder": "",
                    "prepend": "",
                    "append": "",
                    "maxlength": ""
                },
                {
                    "key": "field_633e32e921a5c",
                    "label": "Button Text Color",
                    "name": "button_text_color",
                    "type": "color_picker",
                    "instructions": "",
                    "required": 0,
                    "conditional_logic": 0,
                    "wrapper": {
                        "width": "",
                        "class": "",
                        "id": ""
                    },
                    "default_value": "",
                    "enable_opacity": 0,
                    "return_format": "string"
                },
                {
                    "key": "field_62af6b94c38b2",
                    "label": "Button BG Color",
                    "name": "button_color",
                    "type": "color_picker",
                    "instructions": "",
                    "required": 0,
                    "conditional_logic": 0,
                    "wrapper": {
                        "width": "",
                        "class": "",
                        "id": ""
                    },
                    "default_value": "",
                    "enable_opacity": 0,
                    "return_format": "string"
                },
                {
                    "key": "field_62af6b9dc38b3",
                    "label": "Button Size",
                    "name": "button_size",
                    "type": "button_group",
                    "instructions": "",
                    "required": 0,
                    "conditional_logic": 0,
                    "wrapper": {
                        "width": "",
                        "class": "",
                        "id": ""
                    },
                    "choices": {
                        "default": "Default",
                        "xs": "XS",
                        "sm": "SM",
                        "md": "MD",
                        "lg": "LG",
                        "xl": "XL"
                    },
                    "allow_null": 0,
                    "default_value": "",
                    "layout": "horizontal",
                    "return_format": "value"
                },
                {
                    "key": "field_62af6e2dcde46",
                    "label": "Button Link",
                    "name": "button_link",
                    "type": "link",
                    "instructions": "",
                    "required": 0,
                    "conditional_logic": 0,
                    "wrapper": {
                        "width": "",
                        "class": "",
                        "id": ""
                    },
                    "return_format": "array"
                }
            ]
        }
    ],
    "location": [
        [
            {
                "param": "post_type",
                "operator": "==",
                "value": "post"
            }
        ]
    ],
    "menu_order": 0,
    "position": "normal",
    "style": "default",
    "label_placement": "left",
    "instruction_placement": "label",
    "hide_on_screen": "",
    "active": false,
    "description": "",
    "show_in_rest": 0,
    "acfe_display_title": "",
    "acfe_autosync": [
        "json"
    ],
    "acfe_form": 0,
    "acfe_meta": "",
    "acfe_note": "",
    "modified": 1665020672,
    "acfe_categories": {
        "components": "Components"
    }
}